{
  "updated": "2025-11-18T10:14:22.254920Z",
  "feeds": [
    {
      "source": "detik.com",
      "title": "Ada Proyek Gorong-gorong di Jalan Depan Mal Cinere, Polisi Terapkan Contraflow"
    },
    {
      "source": "antaranews.com",
      "title": "KPK serahkan penanganan kasus Google Cloud ke Kejaksaan Agung"
    },
    {
      "source": "kompas.com",
      "title": "Jemaah Haji 2026 Bakal Dapat 84 Kali Makan di Mekkah, 27 Kali Makan di Madinah"
    },
    {
      "source": "tempo.co",
      "title": "BGN akan Tinjau Ulang Kepemilikan 41 SPPG oleh Anak Wakil Ketua DPRD Sulsel"
    }
  ]
}