{
  "updated": "2025-11-04T11:10:27.091983Z",
  "feeds": [
    {
      "source": "detik.com",
      "title": "Warga Baduy Dibegal di Jakpus Alami Luka, Sempat Tangkis Celurit Pelaku"
    },
    {
      "source": "antaranews.com",
      "title": "Polda Metro Jaya ambil alih kasus temuan kerangka manusia di Kwitang"
    },
    {
      "source": "kompas.com",
      "title": "Harga Bitcoin Terus Melemah, Masih Tepat untuk Beli BTC?"
    },
    {
      "source": "tempo.co",
      "title": "Zulhas: Keberhasilan Pemerintahan Prabowo Bergantung pada Kesuksesan MBG"
    }
  ]
}