{
  "updated": "2025-11-14T17:10:49.459852Z",
  "feeds": [
    {
      "source": "detik.com",
      "title": "Heboh Temuan Cacing Tanah pada Sajian MBG di SMAN 6 Medan"
    },
    {
      "source": "antaranews.com",
      "title": "Bank Tanah-Pemprov Jabar sepakat optimalkan tanah negara untuk publik"
    },
    {
      "source": "kompas.com",
      "title": "Kata-kata Gerald Vanenburg Jelang Laga Timnas U22 Indonesia Vs Mali"
    },
    {
      "source": "tempo.co",
      "title": "Deras Penolakan Gelar Pahlawan Soeharto, Bahlil: Kesempurnaan Hanya Milik Ilahi"
    }
  ]
}