{
  "updated": "2025-11-22T02:21:02.115139Z",
  "feeds": [
    {
      "source": "detik.com",
      "title": "Ketua KPK: Dari Dulu Uang Sitaan Sering Ditampilkan, Bentuk Transparansi"
    },
    {
      "source": "antaranews.com",
      "title": "BMKG: Waspada cuaca panas, hujan petir hingga banjir rob pada Sabtu"
    },
    {
      "source": "kompas.com",
      "title": "Saat Jokowi Tampil di Forum Internasional, Banggakan \"Legacy\" Selama 10 Tahun"
    },
    {
      "source": "tempo.co",
      "title": "Gus Yahya Dilengserkan Syuriyah, PWNU DKI: Kami Hargai Semua Pendapat"
    }
  ]
}