{
  "updated": "2025-11-02T06:16:08.071182Z",
  "feeds": [
    {
      "source": "detik.com",
      "title": "Damkar Evakuasi Tangan Balita Terjepit Pintu Puskesmas di Cimanggis"
    },
    {
      "source": "antaranews.com",
      "title": "Prabowo ajak APEC bantu RI kejar capaian teknologi dan pendidikan"
    },
    {
      "source": "kompas.com",
      "title": "Waspada! Ini 6 Ciri HP yang Sudah Diretas"
    },
    {
      "source": "tempo.co",
      "title": "Pakubuwono XIII Akan Dimakamkan di Imogiri, Upacara Adat Digelar Penuh"
    }
  ]
}