{
  "updated": "2025-10-30T18:15:49.961196Z",
  "feeds": [
    {
      "source": "detik.com",
      "title": "Wakapolri Tinjau Peningkatan Pelayanan SPKT di Denpasar: Polri Harus Hadir"
    },
    {
      "source": "antaranews.com",
      "title": "10 pasien dari luar negeri mulai dirujuk pengobatan ke RS BUMN di Bali"
    },
    {
      "source": "kompas.com",
      "title": "Hingga Tengah Malam, Kemang Raya Masih Lumpuh, Antasari Macet Parah"
    },
    {
      "source": "tempo.co",
      "title": "UGM Desak Pemerintah Beri Perlindungan Hukum Korban MBG"
    }
  ]
}