{
  "updated": "2026-01-02T07:17:20.136066Z",
  "feeds": [
    {
      "source": "detik.com",
      "title": "Polisi Selidiki Penyebab Kematian 3 Orang Sekeluarga di Jakut"
    },
    {
      "source": "antaranews.com",
      "title": "Rob diprediksi landa pesisir Jakarta selama sepekan awal Januari 2026"
    },
    {
      "source": "kompas.com",
      "title": "Harga Emas dan Perak Naik pada Perdagangan Perdana 2026"
    },
    {
      "source": "tempo.co",
      "title": "KSPI Siap Gugat Penetapan UMP Jakarta 2026 ke PTUN"
    },
    {
      "source": "republika.co.id",
      "title": "Perkuat Standar Layanan Transportasi Premium, Juragan 99 Trans Luncurkan Dua Unit Jetbus"
    },
    {
      "source": "viva.co",
      "title": "Tepis Isu Cerai, Audi Marissa dan Anthony Xie Rayakan Malam Tahun Baru 2026 Bersama"
    },
    {
      "source": "jpnn.com",
      "title": "BGN Bangun 19.188 SPPG untuk Program MBG pada 2025"
    },
    {
      "source": "times.co.id",
      "title": "Perkuat Evaluasi dan Regenerasi, UKM JQH Unisma Gelar Musyawarah Akbar Tahunan (MUSYAKTA) XVII"
    },
    {
      "source": "BBC Indonesia",
      "title": "Yang perlu diketahui tentang RUU Pilkada"
    },
    {
      "source": "antaranews Jogja",
      "title": "Komnas HAM: 2026, pemenuhan-penegakan HAM harus terus digaungkan"
    }
  ]
}