{
  "updated": "2025-12-01T11:10:57.141400Z",
  "feeds": [
    {
      "source": "detik.com",
      "title": "Momen Andre Rosiade Dampingi Prabowo Kunjungi Korban Banjir di Sumbar"
    },
    {
      "source": "antaranews.com",
      "title": "Bupati Aceh Tamiang: 10 kecamatan belum bisa diakses bantuan"
    },
    {
      "source": "kompas.com",
      "title": "Warga TPU Kebon Nanas Pertanyakan Relokasi Usai Puluhan Tahun Tinggal di Lahan Makam"
    },
    {
      "source": "tempo.co",
      "title": "Soal Bencana Sumatera, Ketua MPR Minta Pemerintah Evaluasi Kebijakan Lingkungan"
    }
  ]
}