{
  "updated": "2025-11-26T20:12:50.348860Z",
  "feeds": [
    {
      "source": "detik.com",
      "title": "Di Liga Muslim Dunia, Muzani Bicara soal Pancasila dan Keberagaman RI"
    },
    {
      "source": "antaranews.com",
      "title": "RI akan umumkan isu prioritas untuk pencalonan Presiden Dewan HAM PBB"
    },
    {
      "source": "kompas.com",
      "title": "Sucor AM: Kenaikan Jumlah Investor Muda Sinyal Positif bagi Industri Reksa Dana"
    },
    {
      "source": "tempo.co",
      "title": "TNI AD Targetkan Tambah 16 Kodam Baru hingga 2029"
    }
  ]
}