{
  "updated": "2026-01-03T08:15:33.829399Z",
  "feeds": [
    {
      "source": "detik.com",
      "title": "Anak Umur Di bawah 17 Tahun Bisa Bikin Paspor, Ini Syaratnya"
    },
    {
      "source": "antaranews.com",
      "title": "Ledakan dahsyat terdengar di Caracas di tengah ketegangan Venezuela-AS"
    },
    {
      "source": "kompas.com",
      "title": "4 Shio Ini Diprediksi Berbahagia dalam Cinta di 2026, Ada Shio Macan"
    },
    {
      "source": "tempo.co",
      "title": "Menag: AI Tanpa Panduan Agama Berpotensi Dehumanisasi"
    },
    {
      "source": "republika.co.id",
      "title": "Resmi! PSSI Tunjuk John Herdman Arsiteki Timnas Garuda"
    },
    {
      "source": "viva.co",
      "title": "Inara Rusli Pengin Punya Buku Nikah, Kuasa Hukum Singgung Isbat Hingga Poligami"
    },
    {
      "source": "jpnn.com",
      "title": "Gunung Semeru Erupsi 4 Kali, Tinggi Letusan Capai 1.000 Meter"
    },
    {
      "source": "times.co.id",
      "title": "Pesan Damai dalam Nuansa Moderasi Saat Peringatan HAB Kemenag di Kabupaten Malang"
    },
    {
      "source": "BBC Indonesia",
      "title": "Yang perlu diketahui tentang RUU Pilkada"
    },
    {
      "source": "antaranews Jogja",
      "title": "Verstappen masih berkomunikasi dengan mantan bos Red Bull"
    }
  ]
}