{
  "updated": "2026-01-15T00:57:20.252269Z",
  "feeds": [
    {
      "source": "detik.com",
      "title": "KPU Segera Rapat Tindak Lanjuti Putusan KIP soal Keterbukaan Ijazah Jokowi"
    },
    {
      "source": "antaranews.com",
      "title": "Keluarga berperan penting dalam pencegahan perkawinan anak"
    },
    {
      "source": "kompas.com",
      "title": "Harga HP Xiaomi, Redmi, dan Poco di Indonesia Naik, Ini Daftarnya"
    },
    {
      "source": "tempo.co",
      "title": "Hujan Kritik Kebijakan Pegawai SPPG Diangkat Jadi PPPK"
    },
    {
      "source": "republika.co.id",
      "title": "KPK Duga Ketua PBNU Aizzudin Abdurrahman Jadi Perantara di Kasus Yaqut"
    },
    {
      "source": "viva.co",
      "title": "KPK Duga Ketua PBNU Aizzudin Abdurrahman Jadi Perantara Kasus Kuota Haji"
    },
    {
      "source": "jpnn.com",
      "title": "5 Manfaat Teh Celup, Ampuh Atasi Bau Tidak Sedap"
    },
    {
      "source": "times.co.id",
      "title": "Tanpa Lagu, Film “Sebelum Dijemput Nenek” Pilih Teror yang Lebih Sinematik"
    },
    {
      "source": "BBC Indonesia",
      "title": "Yang perlu diketahui tentang RUU Pilkada"
    },
    {
      "source": "antaranews Jogja",
      "title": "Arsenal atasi perlawanan Chelsea, menang tipis 3-2"
    }
  ]
}