{
  "updated": "2026-01-11T15:11:31.304200Z",
  "feeds": [
    {
      "source": "detik.com",
      "title": "Ratas di Hambalang, Prabowo Ingin RI ke Depan Garap Industri Chip"
    },
    {
      "source": "antaranews.com",
      "title": "PTDI \"hidupkan\" kembali CN235 guna perkuat operasi militer di Papua"
    },
    {
      "source": "kompas.com",
      "title": "Bantah Biaya Bongkar Tiang Monorel Rp 100 Miliar, Pramono: Untuk Perbaikan Jalan"
    },
    {
      "source": "tempo.co",
      "title": "Cerita Korban Tempuh 14 Jam ke Banda Aceh Demi Beli Susu"
    },
    {
      "source": "republika.co.id",
      "title": "Rosan Roeslani dan Ferry Juliantono Jadi Pimpinan Masyarakat Ekonomi Syariah"
    },
    {
      "source": "viva.co",
      "title": "Beckham Putra soal Selebrasi Ice Cold usai Bobol Gawang Persija: Ini Sudah Ikonik Bagi Saya"
    },
    {
      "source": "jpnn.com",
      "title": "Diduga Mengantuk, Minibus Terguling di Kalirungkut Surabaya, Pengemudi Luka Serius"
    },
    {
      "source": "times.co.id",
      "title": "Trailer The Death of Robin Hood Dirilis, Hugh Jackman Penuh Sesal"
    },
    {
      "source": "BBC Indonesia",
      "title": "Yang perlu diketahui tentang RUU Pilkada"
    },
    {
      "source": "antaranews Jogja",
      "title": "Mendagri beri  pemda waktu 3 hari data rumah rusak akibat bencana Aceh"
    }
  ]
}