{
  "updated": "2025-12-05T19:09:26.392664Z",
  "feeds": [
    {
      "source": "detik.com",
      "title": "Komisi IX DPR Minta Pengawasan Penyakit Korban Bencana Sumatera Diperketat"
    },
    {
      "source": "antaranews.com",
      "title": "Polisi evakuasi 100 KK usai peristiwa longsor di Arjasari Bandung"
    },
    {
      "source": "kompas.com",
      "title": "FIFA Berikan Penghargaan Perdamaian kepada Donald Trump"
    },
    {
      "source": "tempo.co",
      "title": "Bupati Aceh Selatan Pergi Umrah saat Bencana Banjir di Daerahnya"
    }
  ]
}