{
  "updated": "2026-01-15T14:16:53.311313Z",
  "feeds": [
    {
      "source": "detik.com",
      "title": "4 Terdakwa Demo Ricuh Agustus Dituntut 10 Bulan hingga 1 Tahun Penjara"
    },
    {
      "source": "antaranews.com",
      "title": "LPDP 2026 sediakan 5.750 beasiswa untuk genjot kualitas SDM"
    },
    {
      "source": "kompas.com",
      "title": "UMKM Dapat Diskon 50 Persen, Sewa Kontainer di Wisata Air Kalimalang Rp 50 Juta"
    },
    {
      "source": "tempo.co",
      "title": "Bahlil: Prabowo Bicara Energi dan Hilirisasi ke Guru Besar"
    },
    {
      "source": "republika.co.id",
      "title": "Di Balik Barisan Petugas Haji"
    },
    {
      "source": "viva.co",
      "title": "Bos BYD Ungkap Posisi Indonesia di Peta Investasi Global"
    },
    {
      "source": "jpnn.com",
      "title": "Pelajar di Banyuasin Disetubuhi Kakak Ipar hingga Melahirkan, Astaga"
    },
    {
      "source": "times.co.id",
      "title": "Keajaiban Mandi Sebelum Subuh, Dingin tapi Bikin Sehat"
    },
    {
      "source": "BBC Indonesia",
      "title": "Yang perlu diketahui tentang RUU Pilkada"
    },
    {
      "source": "antaranews Jogja",
      "title": "Wamendagri: Sinergi antardaerah kunci atasi persoalan sampah"
    }
  ]
}