{
  "updated": "2025-12-23T23:11:19.962881Z",
  "feeds": [
    {
      "source": "detik.com",
      "title": "4 Fakta 'Keripik Pisang Narkoba' Dimusnahkan Jaksa"
    },
    {
      "source": "antaranews.com",
      "title": "Tiba di Malang, KP2MI serahkan jenazah korban kebakaran di Hong Kong ke keluarga"
    },
    {
      "source": "kompas.com",
      "title": "Jadwal Piala AFF Futsal U16 2025: Indonesia Tantang Vietnam di Laga Kedua"
    },
    {
      "source": "tempo.co",
      "title": "Panglima TNI Mutasi 187 Pati, Kapuspen Freddy Diganti"
    },
    {
      "source": "republika.co.id",
      "title": "Mencermati Kebijakan Gerakan Ayah Mengambil Rapor ke Sekolah"
    },
    {
      "source": "viva.co",
      "title": "Jadwal SIM Keliling Rabu 24 Desember 2025, Cek Lokasi dan Biaya Perpanjangan"
    },
    {
      "source": "jpnn.com",
      "title": "Ini Alasan Insanul Fahmi Tidak Ungkap Status Saat Menikah dengan Inara Rusli"
    },
    {
      "source": "times.co.id",
      "title": "GoTo Merah Putih Perluas Program Beasiswa, Mitra Driver Gojek Kini Ikut Berpeluang"
    },
    {
      "source": "BBC Indonesia",
      "title": "Yang perlu diketahui tentang RUU Pilkada"
    },
    {
      "source": "antaranews Jogja",
      "title": "Kementerian P2MI menerima pemulangan lima jenazah PMI dari Hong Kong"
    }
  ]
}