{
  "updated": "2026-01-06T08:18:43.033445Z",
  "feeds": [
    {
      "source": "detik.com",
      "title": "Soal Usulan Pilkada Via DPRD, Waka DPR Dasco Ajak Fokus Tangani Bencana"
    },
    {
      "source": "antaranews.com",
      "title": "Sudah sebulan masalah sampah di Tangsel tak kunjung selesai"
    },
    {
      "source": "kompas.com",
      "title": "Prabowo: Sebagai Presiden, Saya Sampaikan Terima Kasih ke Pembantu-pembantu Saya"
    },
    {
      "source": "tempo.co",
      "title": "Asuransi Jasindo Mantapkan Narasemesta Jadi Fondasi Keberlanjutan di 2026"
    },
    {
      "source": "republika.co.id",
      "title": "ESDM: Dampak Konflik Venezuela tak Signifikan ke Harga Minyak Dunia"
    },
    {
      "source": "viva.co",
      "title": "Harga 3 Motor Honda Lebih Murah Rp6 Jutaan di Awal Tahun 2026"
    },
    {
      "source": "jpnn.com",
      "title": "Kuburan Band Klarifikasi Lagu Tak Diberi Tulang Lagi yang Bikin Heboh"
    },
    {
      "source": "times.co.id",
      "title": "Pemkab Mojokerto dan FK Ubaya Perkuat Percepatan Penurunan Stunting"
    },
    {
      "source": "BBC Indonesia",
      "title": "Yang perlu diketahui tentang RUU Pilkada"
    },
    {
      "source": "antaranews Jogja",
      "title": "Retret Hambalang, Prabowo pertajam arah kebijakan 2026"
    }
  ]
}