{
  "updated": "2025-12-21T12:21:02.484192Z",
  "feeds": [
    {
      "source": "detik.com",
      "title": "Apa Itu Hamburan Rayleigh yang Bikin Heboh Langit Merah di Pandeglang?"
    },
    {
      "source": "antaranews.com",
      "title": "Dirut PLN: Listrik Aceh pulih, seluruh Gardu Induk beroperasi normal"
    },
    {
      "source": "kompas.com",
      "title": "Tol Termahal di Indonesia, Becakayu, Diskon 20 Persen Saat Nataru"
    },
    {
      "source": "tempo.co",
      "title": "Rapimnas Golkar Usul Pembentukan Koalisi Permanen"
    },
    {
      "source": "republika.co.id",
      "title": "Bandara Abdulrachman Saleh Buka Rute Baru ke Lombok"
    },
    {
      "source": "viva.co",
      "title": "Detik-detik Pengemudi Camry Mabuk Tabrak Honda Civic di Bandung, 9 Orang Luka"
    },
    {
      "source": "jpnn.com",
      "title": "Tutup 2025 dengan Kemenangan atas Sevilla, Real Madrid Berjuang Merebut Semua Gelar di 2026"
    },
    {
      "source": "times.co.id",
      "title": "Dorong Budaya Inklusi, Pranata Humas Fapet UGM Sabet Tendik Berprestasi 2025"
    },
    {
      "source": "BBC Indonesia",
      "title": "Yang perlu diketahui tentang RUU Pilkada"
    },
    {
      "source": "antaranews Jogja",
      "title": "Kemenkop dan DJP membangun ekosistem data koperasi terintegrasi"
    }
  ]
}