{
  "updated": "2026-01-17T00:57:10.989000Z",
  "feeds": [
    {
      "source": "detik.com",
      "title": "Kakorlantas Polri Distribusikan ETLE Mobile Handheld Presisi ke Seluruh Indonesia"
    },
    {
      "source": "antaranews.com",
      "title": "Jalur KA di Pekalongan terputus akibat terendam banjir"
    },
    {
      "source": "kompas.com",
      "title": "Oliver Glasner Akan Tinggalkan Crystal Palace, Man United Siap Tampung?"
    },
    {
      "source": "tempo.co",
      "title": "Top 3: Dukungan Pilpres 2029 hingga Pegawai MBG jadi PPPK"
    },
    {
      "source": "republika.co.id",
      "title": "Pernah Jadi Raja OTT KPK, Pejabat Kemenhaj Ini Mulai Panggil Sejumlah KBIH dan PIHK"
    },
    {
      "source": "viva.co",
      "title": "Petani Bakal Digaji Pemerintah untuk Pulihkan Sawah Terdampak Bencana Sumatera"
    },
    {
      "source": "jpnn.com",
      "title": "Daftar Kereta Api Memutar & Batal Akibat Banjir di Pekalongan"
    },
    {
      "source": "times.co.id",
      "title": "President Prabowo Fully Supports Sasakawa Foundation&apos;s Efforts to Eradicate Leprosy in Indonesia"
    },
    {
      "source": "BBC Indonesia",
      "title": "Yang perlu diketahui tentang RUU Pilkada"
    },
    {
      "source": "antaranews Jogja",
      "title": "Atalanta ditahan imbang Pisa 1-1"
    }
  ]
}