{
  "updated": "2025-12-30T06:19:43.810990Z",
  "feeds": [
    {
      "source": "detik.com",
      "title": "Istri Dianiaya Suami hingga Buta di Depok Diberi Pendampingan Psikologis"
    },
    {
      "source": "antaranews.com",
      "title": "Polri fokuskan pengamanan aksi massa dengan pendekatan humanis"
    },
    {
      "source": "kompas.com",
      "title": "Mulai 1 Januari 2026, Petani Sudah Bisa Tebus Pupuk Subsidi"
    },
    {
      "source": "tempo.co",
      "title": "Wacana Pilkada Dipilih DPRD, PKS: Perlu Ada Recall Politik"
    },
    {
      "source": "republika.co.id",
      "title": "Preman di Sumedang yang Viral Ancam Bakar Minimarket Ditangkap"
    },
    {
      "source": "viva.co",
      "title": "Jaga Stabilitas Harga dan Pasokan, Zulhas Targetkan Cadangan Beras 4 Juta Ton di 2026"
    },
    {
      "source": "jpnn.com",
      "title": "Stink Breath Menyongsong Babak Baru Lewat Best On 70’s"
    },
    {
      "source": "times.co.id",
      "title": "Polres Banjarnegara Ungkap 120 Kasus Sepanjang Tahun 2025, Ini Rinciannya"
    },
    {
      "source": "BBC Indonesia",
      "title": "Yang perlu diketahui tentang RUU Pilkada"
    },
    {
      "source": "antaranews Jogja",
      "title": "Kemenko Pangan tetapkan neraca garam CAP 2026 sebesar 1,18 juta ton"
    }
  ]
}