{
  "updated": "2025-12-25T06:19:19.721941Z",
  "feeds": [
    {
      "source": "detik.com",
      "title": "Cerita Mang Apip dari Sekuriti Jadi 'Joki Jalur' Resmi di Puncak Bogor"
    },
    {
      "source": "antaranews.com",
      "title": "Garda Revolusi Iran sita kapal tanker asing berisi BBM selundupan"
    },
    {
      "source": "kompas.com",
      "title": "Daftar Lengkap Tim ACL 2 yang Lolos Babak 16 Besar: Al Nassr Juara Grup"
    },
    {
      "source": "tempo.co",
      "title": "BGN: Makanan Ultra Proses Bisa Dikonsumsi Asal Tak Berlebih"
    },
    {
      "source": "republika.co.id",
      "title": "Rais Aam dan Ketum PBNU Hadiri Pertemuan di Lirboyo Hari Ini"
    },
    {
      "source": "viva.co",
      "title": "Rainbow Six Siege X Resmi Meluncur, Update Terbesar Sepanjang Sejarah Siap Ubah Pengalaman Bermain"
    },
    {
      "source": "jpnn.com",
      "title": "KLH Perkuat Aturan EPR Lewat Perpres, Target Rampung Semester I 2026"
    },
    {
      "source": "times.co.id",
      "title": "Pengamanan Ketat Ibadah Natal di Bondowoso, Tim Gabungan Jaga Gereja"
    },
    {
      "source": "BBC Indonesia",
      "title": "Yang perlu diketahui tentang RUU Pilkada"
    },
    {
      "source": "antaranews Jogja",
      "title": "Pemkab Agam terbitkan 1.223 dokumen kependudukan korban bencana alam"
    }
  ]
}