{
  "updated": "2026-01-11T04:40:08.385383Z",
  "feeds": [
    {
      "source": "detik.com",
      "title": "KPK Tak Pajang Tersangka OTT Pajak, Ini Aturannya di KUHAP Baru"
    },
    {
      "source": "antaranews.com",
      "title": "Trump dikabarkan minta rencana invasi ke Greenland"
    },
    {
      "source": "kompas.com",
      "title": "Bernardo Tavares Terkesan Dukungan Bonek saat Persebaya Kalahkan Malut United"
    },
    {
      "source": "tempo.co",
      "title": "Maruarar: Pembangunan Hunian Tetap di Aceh Dimulai Februari"
    },
    {
      "source": "republika.co.id",
      "title": "UEA Ikut Latihan Militer dengan Saudi, Hubungan Mencair?"
    },
    {
      "source": "viva.co",
      "title": "Mengerikan! 14 Rumah dan Konveksi di Tambora Kebakaran, Kerugian Capai Rp1,7 M, Penyebabnya Ternyata..."
    },
    {
      "source": "jpnn.com",
      "title": "KPK Tangkap 8 Orang Dugaan Korupsi Pajak Pertambangan Rp75 Miliar"
    },
    {
      "source": "times.co.id",
      "title": "Sony Pictures Matangkan Konsep Semesta Spider&Man, Rencana Bikin Spider&Woman Ditunda"
    },
    {
      "source": "BBC Indonesia",
      "title": "Yang perlu diketahui tentang RUU Pilkada"
    },
    {
      "source": "antaranews Jogja",
      "title": "Otorita IKN dorong aktivitas ekonomi dan lapangan kerja"
    }
  ]
}