{
  "updated": "2026-01-07T08:18:21.006480Z",
  "feeds": [
    {
      "source": "detik.com",
      "title": "Densus 88 Duga Aksi Penikaman di Rusia Terinspirasi Insiden Ledakan di SMAN 72 Jakarta"
    },
    {
      "source": "antaranews.com",
      "title": "Polresta Yogyakarta bongkar sindikat \"love scamming\" internasional"
    },
    {
      "source": "kompas.com",
      "title": "PKB soal Diawasi Prabowo: Rekam Jejak Kami Setia dan Dapat Diandalkan"
    },
    {
      "source": "tempo.co",
      "title": "Panitia SNPMB: Nilai TKA Penentu Siswa Eligible SNBP 2026"
    },
    {
      "source": "republika.co.id",
      "title": "Ketua KPK Bantah Perpecahan Internal Akibat Perkara Kuota Haji"
    },
    {
      "source": "viva.co",
      "title": "Ammar Zoni Sengaja Pakai Narkoba Biar DIpenjara Lagi? Irish Bella Diduga Jadi Penyebabnya"
    },
    {
      "source": "jpnn.com",
      "title": "Lewat Alas Roban, Michelle Ziudith Debut Film Horor"
    },
    {
      "source": "times.co.id",
      "title": "Bupati Sumba Timur Ajak Perusahaan dan Petani Optimalkan Potensi Budidaya Rumput Laut"
    },
    {
      "source": "BBC Indonesia",
      "title": "Yang perlu diketahui tentang RUU Pilkada"
    },
    {
      "source": "antaranews Jogja",
      "title": "KPK: Pengembangan kasus Bupati Bekasi ke Eddy lihat hasil pemeriksaan"
    }
  ]
}